gap/pkg/curlinterface/CHANGES
gap/pkg/curlinterface/GPL
gap/pkg/curlinterface/LICENSE
gap/pkg/curlinterface/PackageInfo.g
gap/pkg/curlinterface/README.md
gap/pkg/curlinterface/init.g
gap/pkg/curlinterface/makedoc.g
gap/pkg/curlinterface/read.g
gap/pkg/curlinterface/bin/aarch64-unknown-linux-gnu-default64-kv10/curl.so
gap/pkg/curlinterface/gap/curl.gd
gap/pkg/curlinterface/gap/curl.gi
gap/pkg/curlinterface/tst/basic.tst
gap/pkg/curlinterface/tst/errors.tst
gap/pkg/curlinterface/tst/testall.g
passagemath_gap_pkg_curlinterface/__init__.py
passagemath_gap_pkg_curlinterface.libs/libcrypto-47efeb7f.so.3
passagemath_gap_pkg_curlinterface.libs/libcurl-ef5189c4.so.4.8.0
passagemath_gap_pkg_curlinterface.libs/libssl-3ce7200b.so.3
sage/all__sagemath_gap_pkg_curlinterface.py
sage/libs/all__sagemath_gap_pkg_curlinterface.py
sage/libs/gap_pkg_curlinterface.cpython-314t-aarch64-linux-gnu.so
passagemath_gap_pkg_curlinterface-10.6.43.dist-info/METADATA
passagemath_gap_pkg_curlinterface-10.6.43.dist-info/METADATA.bak
passagemath_gap_pkg_curlinterface-10.6.43.dist-info/WHEEL
passagemath_gap_pkg_curlinterface-10.6.43.dist-info/top_level.txt
passagemath_gap_pkg_curlinterface-10.6.43.dist-info/RECORD
